Metadata-Version: 1.1
Name: watson-developer-cloud
Version: 2.5.1
Summary: Client library to use the IBM Watson Services
Home-page: https://github.com/watson-developer-cloud/python-sdk
Author: Jeffrey Stylos
Author-email: jsstylos@us.ibm.com
License: Apache 2.0
Keywords: language,vision,question and answer tone_analyzer,natural language classifier,text to speech,language translation,language identification,concept expansion,machine translation,personality insights,message resonance,watson developer cloud,wdc,watson,ibm,dialog,user modeling,tone analyzer,speech to text,visual recognition
Platform: UNKNOWN
Classifier: Programming Language :: Python
Classifier: Programming Language :: Python :: 2
Classifier: Programming Language :: Python :: 3
Classifier: Development Status :: 4 - Beta
Classifier: Intended Audience :: Developers
Classifier: License :: OSI Approved :: Apache Software License
Classifier: Operating System :: OS Independent
Classifier: Topic :: Software Development :: Libraries :: Python Modules
Classifier: Topic :: Software Development :: Libraries :: Application Frameworks
